bioportal/__init__.py
bioportal/bioportal_client.py
bioportal-apis/__init__.py
bioportal-apis/bioportal_client.py
bioportal-0.0.5.dist-info/LICENSE
bioportal-0.0.5.dist-info/METADATA
bioportal-0.0.5.dist-info/WHEEL
bioportal-0.0.5.dist-info/top_level.txt
bioportal-0.0.5.dist-info/RECORD
