Metadata-Version: 2.1
Name: bioportal
Version: 0.0.5
Summary: BioPortal APIs es un paquete de Python que permite accesar las bases de datos públicas del BioPortal del Departamento de Salud de Puerto Rico.
Home-page: https://github.com/jmzg1229/bioportal-apis
Author: José Zavala González
Author-email: jose.zavala@salud.pr.gov
License: UNKNOWN
Platform: UNKNOWN
Classifier: Programming Language :: Python :: 3
Classifier: License :: OSI Approved :: MIT License
Classifier: Operating System :: OS Independent
Classifier: Development Status :: 3 - Alpha
Requires-Python: >=3.6
Requires-Dist: brotlipy
Requires-Dist: requests
Requires-Dist: pandas (>=1.0.3)
